cravensworth/__init__.py
cravensworth/contrib/db/__init__.py
cravensworth/contrib/db/admin.py
cravensworth/contrib/db/apps.py
cravensworth/contrib/db/models.py
cravensworth/contrib/db/tests.py
cravensworth/contrib/db/views.py
cravensworth/contrib/db/migrations/__init__.py
cravensworth/core/__init__.py
cravensworth/core/apps.py
cravensworth/core/conf.py
cravensworth/core/decorators.py
cravensworth/core/experiment.py
cravensworth/core/middleware.py
cravensworth/core/source.py
cravensworth/core/utils.py
cravensworth/core/templatetags/__init__.py
cravensworth/core/templatetags/cravensworth.py
django_cravensworth-1.0.0.dist-info/licenses/LICENSE
django_cravensworth-1.0.0.dist-info/METADATA
django_cravensworth-1.0.0.dist-info/WHEEL
django_cravensworth-1.0.0.dist-info/top_level.txt
django_cravensworth-1.0.0.dist-info/RECORD
