Metadata-Version: 2.4
Name: django-cravensworth
Version: 1.0.0
Summary: A Django app for experimentation.
Author: Daniel Merritt
License-Expression: BSD-3-Clause
Project-URL: Homepage, https://django-cravensworth.readthedocs.io
Classifier: Environment :: Web Environment
Classifier: Framework :: Django
Classifier: Framework :: Django :: 5.2
Classifier: Framework :: Django :: 6.0
Classifier: Intended Audience :: Developers
Classifier: Operating System :: OS Independent
Classifier: Programming Language :: Python
Classifier: Programming Language :: Python :: 3
Classifier: Programming Language :: Python :: 3 :: Only
Classifier: Programming Language :: Python :: 3.12
Classifier: Programming Language :: Python :: 3.13
Classifier: Programming Language :: Python :: 3.14
Classifier: Topic :: Internet :: WWW/HTTP
Classifier: Topic :: Internet :: WWW/HTTP :: Dynamic Content
Requires-Python: >=3.12
License-File: LICENSE
Requires-Dist: django>=5.2
Requires-Dist: rapidhash>=0.1.0
Requires-Dist: setuptools-scm>=8.3.1
Requires-Dist: simpleeval>=1.0.3
Dynamic: license-file
